[
  {
    "postId": 216178,
    "label": "[GIF] Had some fun golfing today!",
    "score": 10204,
    "likesCount": 10524,
    "userId": "96b9822c-60b6-4ae3-8478-cc6ece5a8771",
    "mediaId": "e2da282e-5989-49b7-88e4-3540e06e2a8c",
    "duration": 29,
    "viewsCount": 2032762,
    "bunnyVideoId": "ea29b07b-e147-46f1-b9a1-3036c82cac59",
    "isBunnyVideoReady": true,
    "linkDescription": null,
    "linkSidebar": null,
    "createdAt": "2022-10-06T11:37:28.084Z",
    "updatedAt": "2025-09-28T11:00:37.240Z",
    "deletedAt": null,
    "uploadMethod": null,
    "sexualOrientation": "STRAIGHT",
    "algorithm": "random-silver-posts",
    "videoStreamUrl": "https://vz-5d293dac-178.b-cdn.net/bcdn_token=wFpCpLchtHcCtS93sS-3YRgf8Hhm6_-OlsEfdyrFf2s&token_countries=IN&token_path=%2Fea29b07b-e147-46f1-b9a1-3036c82cac59%2F&expires=1759065706/ea29b07b-e147-46f1-b9a1-3036c82cac59/playlist.m3u8",
    "thumbnailStreamUrl": "https://vz-5d293dac-178.b-cdn.net/ea29b07b-e147-46f1-b9a1-3036c82cac59/thumbnail.jpg?token=pTEiSy38nsFr1liR-UHsxaJts9Q0O9Nym8eC6yResFc&height=854&token_countries=IN&width=480&expires=1759065706",
    "publishedAt": "2024-11-04T07:20:02.085Z",
    "inCollectionsCount": 937,
    "commentsCount": 0,
    "explicitnessRating": "PARTIAL_NUDITY",
    "author": {
      "userId": "96b9822c-60b6-4ae3-8478-cc6ece5a8771",
      "username": "grabdreamlike",
      "countPosts": 211,
      "countIncomingLikes": 712430,
      "countIncomingFollows": 116943,
      "countOutgoingLikes": 0,
      "countOutgoingFollows": 0,
      "countCollections": 0,
      "countTotalViews": 163603837,
      "thumbnailId": null,
      "isSignedUp": true,
      "isVerified": true,
      "isPartner": true,
      "isAmbassador": false,
      "isStaff": false,
      "lastSeenAt": "2024-12-08T05:04:50.589Z",
      "description": null,
      "createdAt": "2023-01-28T00:20:57.301Z",
      "updatedAt": "2025-09-25T01:33:21.394Z",
      "deletedAt": null,
      "thumbnailUrl": null,
      "roles": [],
      "profileLinks": [
        {
          "profileLinkId": "c79e0e7b-d9ad-46b4-8c7e-bd659a81cb5b",
          "userId": "96b9822c-60b6-4ae3-8478-cc6ece5a8771",
          "type": "ONLYFANS",
          "url": "https://onlyfans.com/anastasiagoth",
          "location": "PROFILE"
        },
        {
          "profileLinkId": "b12c8552-8c92-49ab-8092-59c27245ed20",
          "userId": "96b9822c-60b6-4ae3-8478-cc6ece5a8771",
          "type": "TWITTER",
          "url": "https://twitter.com/gothspvtsuicide",
          "location": "PROFILE"
        }
      ]
    },
    "hashtags": [
      {
        "hashtagId": "85a84b56-5ec2-40b1-89b4-51d1dad79ee5",
        "label": "holdthemoan",
        "labelLower": "holdthemoan",
        "description": "Kinky girls that dare to get naughty at inappropriate times and risky places! Sometimes unable to hold their moans.",
        "createdAt": "2023-09-05T11:03:51.712Z",
        "updatedAt": "2025-09-17T03:00:31.491Z",
        "countPosts": 188,
        "countFollows": 16703,
        "lastCountUpdatedAt": "2025-09-17T03:00:30.591Z",
        "thumbnailPostId": 249936,
        "sexualOrientations": [
          "STRAIGHT",
          "LESBIAN",
          "GAY",
          "TRANS",
          "OTHER"
        ],
        "isModerated": true,
        "searchTags": []
      }
    ]
  },
  {
    "postId": 779014,
    "label": "fucking time💦",
    "score": 7989,
    "likesCount": 9429,
    "userId": "f16ff3a5-d1f8-4e29-9167-44b6d594a234",
    "mediaId": "a02be762-c072-47ae-bf21-bbb352f87559",
    "duration": null,
    "viewsCount": 2187009,
    "bunnyVideoId": "7283dff6-e32e-4362-8bd3-79c75fb20dc5",
    "isBunnyVideoReady": true,
    "linkDescription": {
      "profileLinkId": "a2026ead-dcfd-4e28-ae70-7d98c04a7dc5",
      "userId": "f16ff3a5-d1f8-4e29-9167-44b6d594a234",
      "type": "ONLYFANS",
      "url": "https://onlyfans.com/resmi",
      "location": "POST_DESCRIPTION"
    },
    "linkSidebar": {
      "profileLinkId": "2803626e-4e3a-41cd-88fa-1c76a8a61c5a",
      "userId": "f16ff3a5-d1f8-4e29-9167-44b6d594a234",
      "type": "OTHER",
      "url": "https://x.com/resmi_r_nair",
      "location": "POST_SIDEBAR"
    },
    "createdAt": "2024-12-15T01:19:43.495Z",
    "updatedAt": "2025-09-28T11:00:37.240Z",
    "deletedAt": null,
    "uploadMethod": "USER_FILE",
    "sexualOrientation": "STRAIGHT",
    "algorithm": "random-silver-posts",
    "videoStreamUrl": "https://vz-5d293dac-178.b-cdn.net/bcdn_token=72KIkqjGiUw6bGf-duKod2DfmMuEgUfbiDmhU0sRDFk&token_countries=IN&token_path=%2F7283dff6-e32e-4362-8bd3-79c75fb20dc5%2F&expires=1759065706/7283dff6-e32e-4362-8bd3-79c75fb20dc5/playlist.m3u8",
    "thumbnailStreamUrl": "https://vz-5d293dac-178.b-cdn.net/7283dff6-e32e-4362-8bd3-79c75fb20dc5/thumbnail.jpg?token=GT3l1mb-rndcmCSiC6UWoQ-9AAWBJ5vTIZY2zOQbgpQ&height=854&token_countries=IN&width=480&expires=1759065706",
    "publishedAt": "2024-12-15T01:21:22.510Z",
    "inCollectionsCount": 750,
    "commentsCount": 0,
    "explicitnessRating": "FULLY_EXPLICIT",
    "author": {
      "userId": "f16ff3a5-d1f8-4e29-9167-44b6d594a234",
      "username": "Resmi_R_Nair",
      "countPosts": 76,
      "countIncomingLikes": 308192,
      "countIncomingFollows": 72259,
      "countOutgoingLikes": 4,
      "countOutgoingFollows": 1,
      "countCollections": 0,
      "countTotalViews": 85424388,
      "thumbnailId": "a3324d47-df88-4637-935a-ba6d4beb1fa1",
      "isSignedUp": true,
      "isVerified": true,
      "isPartner": true,
      "isAmbassador": false,
      "isStaff": false,
      "lastSeenAt": "2025-09-21T11:12:23.455Z",
      "description": "Hotwife by passion MILF by profession https://onlyfans.com/resminair",
      "createdAt": "2024-05-01T21:31:57.503Z",
      "updatedAt": "2025-09-25T01:33:22.284Z",
      "deletedAt": null,
      "thumbnailUrl": "https://fikfap-media-prod.b-cdn.net/users/thumbnails/a3324d47-df88-4637-935a-ba6d4beb1fa1.jpg?token=jKI58nD9JImsNedywHWWSGD199_QIS5KJCJ5WHyWT5w&height=224&token_countries=IN&width=224&expires=1759065706",
      "roles": [],
      "profileLinks": [
        {
          "profileLinkId": "58ce09c8-707a-421c-952c-a8e630194641",
          "userId": "f16ff3a5-d1f8-4e29-9167-44b6d594a234",
          "type": "ONLYFANS",
          "url": "https://onlyfans.com/resmi",
          "location": "PROFILE"
        },
        {
          "profileLinkId": "2803626e-4e3a-41cd-88fa-1c76a8a61c5a",
          "userId": "f16ff3a5-d1f8-4e29-9167-44b6d594a234",
          "type": "OTHER",
          "url": "https://x.com/resmi_r_nair",
          "location": "POST_SIDEBAR"
        },
        {
          "profileLinkId": "a2026ead-dcfd-4e28-ae70-7d98c04a7dc5",
          "userId": "f16ff3a5-d1f8-4e29-9167-44b6d594a234",
          "type": "ONLYFANS",
          "url": "https://onlyfans.com/resmi",
          "location": "POST_DESCRIPTION"
        },
        {
          "profileLinkId": "9d805a54-f1eb-4148-8b8c-a081a8a9b7a3",
          "userId": "f16ff3a5-d1f8-4e29-9167-44b6d594a234",
          "type": "INSTAGRAM",
          "url": "https://www.instagram.com/resmirnair_model/",
          "location": "PROFILE"
        }
      ]
    },
    "hashtags": [
      {
        "hashtagId": "489a8b37-f4ef-4eb5-8064-bc953e875525",
        "label": "couplesex",
        "labelLower": "couplesex",
        "description": "",
        "createdAt": "2023-09-05T11:04:06.345Z",
        "updatedAt": "2025-09-17T03:00:33.677Z",
        "countPosts": 4691,
        "countFollows": 14750,
        "lastCountUpdatedAt": "2025-09-17T03:00:30.591Z",
        "thumbnailPostId": 312076,
        "sexualOrientations": [
          "STRAIGHT",
          "LESBIAN",
          "GAY",
          "TRANS",
          "OTHER"
        ],
        "isModerated": false,
        "searchTags": []
      }
    ]
  },
  {
    "postId": 366922,
    "label": "Thick bikini chick in the Park 👀 Uncut version",
    "score": 8046,
    "likesCount": 8886,
    "userId": "d47176b3-4b81-4eb6-a85f-7122ba1d76d3",
    "mediaId": "cf28fc2b-89b8-4c10-8569-54306e3ca70d",
    "duration": 54,
    "viewsCount": 2929684,
    "bunnyVideoId": "9bfc5410-69ba-46f9-8cab-7795df2f8111",
    "isBunnyVideoReady": true,
    "linkDescription": {
      "profileLinkId": "734d2668-7d5a-44de-a8d9-6587243bd6d8",
      "userId": "d47176b3-4b81-4eb6-a85f-7122ba1d76d3",
      "type": "ONLYFANS",
      "url": "https://onlyfans.com/chicktrainer",
      "location": "POST_DESCRIPTION"
    },
    "linkSidebar": {
      "profileLinkId": "c8c74b77-a2fb-4d27-8416-c9fd0e7a99b8",
      "userId": "d47176b3-4b81-4eb6-a85f-7122ba1d76d3",
      "type": "OTHER",
      "url": "https://onlyfans.com/chicktrainer",
      "location": "POST_SIDEBAR"
    },
    "createdAt": "2023-11-16T00:56:13.456Z",
    "updatedAt": "2025-09-28T11:25:36.436Z",
    "deletedAt": null,
    "uploadMethod": "CRAWLER_REDDIT",
    "sexualOrientation": "STRAIGHT",
    "algorithm": "random-silver-posts",
    "videoStreamUrl": "https://vz-5d293dac-178.b-cdn.net/bcdn_token=-T4jIorxlOZ3CkoABvgQAjPc4suTDRwmO1HziQrbkXM&token_countries=IN&token_path=%2F9bfc5410-69ba-46f9-8cab-7795df2f8111%2F&expires=1759065706/9bfc5410-69ba-46f9-8cab-7795df2f8111/playlist.m3u8",
    "thumbnailStreamUrl": "https://vz-5d293dac-178.b-cdn.net/9bfc5410-69ba-46f9-8cab-7795df2f8111/thumbnail.jpg?token=471J_F_-GjhxMYTKUuaAqhQ79aMJ0O0Vd3KVE5ui-ko&height=854&token_countries=IN&width=480&expires=1759065706",
    "publishedAt": "2024-09-22T20:54:08.388Z",
    "inCollectionsCount": 840,
    "commentsCount": 0,
    "explicitnessRating": "PARTIAL_NUDITY",
    "author": {
      "userId": "d47176b3-4b81-4eb6-a85f-7122ba1d76d3",
      "username": "chicktrainer",
      "countPosts": 539,
      "countIncomingLikes": 389056,
      "countIncomingFollows": 83514,
      "countOutgoingLikes": 2,
      "countOutgoingFollows": 0,
      "countCollections": 0,
      "countTotalViews": 139569771,
      "thumbnailId": "d55691fb-6682-4bf6-8016-8987ca853aff",
      "isSignedUp": true,
      "isVerified": true,
      "isPartner": true,
      "isAmbassador": false,
      "isStaff": false,
      "lastSeenAt": "2024-12-12T08:34:09.191Z",
      "description": "Britney Swallows",
      "createdAt": "2022-12-23T08:49:46.277Z",
      "updatedAt": "2025-09-25T01:33:21.006Z",
      "deletedAt": null,
      "thumbnailUrl": "https://fikfap-media-prod.b-cdn.net/users/thumbnails/d55691fb-6682-4bf6-8016-8987ca853aff.jpg?token=eccJFeGM6viVfubUy-TU-ICGIxTB15pR8LqPNaolGOo&height=224&token_countries=IN&width=224&expires=1759065706",
      "roles": [],
      "profileLinks": [
        {
          "profileLinkId": "c8c74b77-a2fb-4d27-8416-c9fd0e7a99b8",
          "userId": "d47176b3-4b81-4eb6-a85f-7122ba1d76d3",
          "type": "OTHER",
          "url": "https://onlyfans.com/chicktrainer",
          "location": "POST_SIDEBAR"
        },
        {
          "profileLinkId": "734d2668-7d5a-44de-a8d9-6587243bd6d8",
          "userId": "d47176b3-4b81-4eb6-a85f-7122ba1d76d3",
          "type": "ONLYFANS",
          "url": "https://onlyfans.com/chicktrainer",
          "location": "POST_DESCRIPTION"
        },
        {
          "profileLinkId": "328bdd01-c7af-453e-931d-a5d9d3f372ca",
          "userId": "d47176b3-4b81-4eb6-a85f-7122ba1d76d3",
          "type": "ONLYFANS",
          "url": "https://onlyfans.com/chicktrainer",
          "location": "PROFILE"
        }
      ]
    },
    "hashtags": [
      {
        "hashtagId": "b992f4c5-f93d-49c3-9329-75568046f043",
        "label": "exhibitionist",
        "labelLower": "exhibitionist",
        "description": "",
        "createdAt": "2023-09-05T11:04:04.367Z",
        "updatedAt": "2025-09-17T03:00:34.325Z",
        "countPosts": 1221,
        "countFollows": 15486,
        "lastCountUpdatedAt": "2025-09-17T03:00:30.591Z",
        "thumbnailPostId": 653214,
        "sexualOrientations": [
          "STRAIGHT",
          "LESBIAN",
          "GAY",
          "TRANS",
          "OTHER"
        ],
        "isModerated": false,
        "searchTags": []
      }
    ]
  },
  {
    "postId": 1363292,
    "label": "Watch this lesbian girl in real time on the best site – link in bio!",
    "score": 1368,
    "likesCount": 1408,
    "userId": "6aa1dbd5-3c23-4f2d-9d39-6c480830ca51",
    "mediaId": "4e3b5db0-f02c-4d88-bbc0-c8be64d44eb6",
    "duration": null,
    "viewsCount": 59044,
    "bunnyVideoId": "7ddc948a-c446-4739-9c2e-704709068320",
    "isBunnyVideoReady": true,
    "linkDescription": null,
    "linkSidebar": {
      "profileLinkId": "903b028a-2df8-49c6-84e4-386aec779b2e",
      "userId": "6aa1dbd5-3c23-4f2d-9d39-6c480830ca51",
      "type": "OTHER",
      "url": "https://49dzi.bemobtrcks.com/go/37f9798e-8dae-4e0b-9cbe-5e17a0ced3a3?id=64260312",
      "location": "POST_SIDEBAR"
    },
    "createdAt": "2025-09-15T11:30:23.072Z",
    "updatedAt": "2025-09-28T11:00:39.241Z",
    "deletedAt": null,
    "uploadMethod": "USER_FILE",
    "sexualOrientation": "LESBIAN",
    "algorithm": "random-silver-posts",
    "videoStreamUrl": "https://vz-5d293dac-178.b-cdn.net/bcdn_token=-RyoQ_uVMDyJEk-Ju8ZZSD2J3Bx1gqw4AAqYb5FiFz4&token_countries=IN&token_path=%2F7ddc948a-c446-4739-9c2e-704709068320%2F&expires=1759065706/7ddc948a-c446-4739-9c2e-704709068320/playlist.m3u8",
    "thumbnailStreamUrl": "https://vz-5d293dac-178.b-cdn.net/7ddc948a-c446-4739-9c2e-704709068320/thumbnail.jpg?token=3D3fdd93tMsbv8nrc41qfwwxBFlQTfgcLa6fgHSQeBA&height=854&token_countries=IN&width=480&expires=1759065706",
    "publishedAt": "2025-09-15T14:25:12.011Z",
    "inCollectionsCount": 39,
    "commentsCount": 0,
    "explicitnessRating": "FULLY_EXPLICIT",
    "author": {
      "userId": "6aa1dbd5-3c23-4f2d-9d39-6c480830ca51",
      "username": "LesbianFun",
      "countPosts": 65,
      "countIncomingLikes": 16812,
      "countIncomingFollows": 2764,
      "countOutgoingLikes": 56,
      "countOutgoingFollows": 0,
      "countCollections": 0,
      "countTotalViews": 566653,
      "thumbnailId": "965b23c3-957a-4432-a442-a2e60e0e0e95",
      "isSignedUp": true,
      "isVerified": true,
      "isPartner": true,
      "isAmbassador": false,
      "isStaff": false,
      "lastSeenAt": "2025-09-22T09:45:36.934Z",
      "description": "See lesbian girls now on the top site 👇",
      "createdAt": "2025-04-14T00:07:02.885Z",
      "updatedAt": "2025-09-22T09:45:36.935Z",
      "deletedAt": null,
      "thumbnailUrl": "https://fikfap-media-prod.b-cdn.net/users/thumbnails/965b23c3-957a-4432-a442-a2e60e0e0e95.jpg?token=Wk9BNeKISRVyUqdTDuk0_QXFPmzB2PikRyW_zS6x15I&height=224&token_countries=IN&width=224&expires=1759065706",
      "roles": [],
      "profileLinks": [
        {
          "profileLinkId": "6050844b-c28f-40c6-9be6-5f1303990a99",
          "userId": "6aa1dbd5-3c23-4f2d-9d39-6c480830ca51",
          "type": "OTHER",
          "url": "https://49dzi.bemobtrcks.com/go/37f9798e-8dae-4e0b-9cbe-5e17a0ced3a3?id=64260312",
          "location": "PROFILE"
        },
        {
          "profileLinkId": "903b028a-2df8-49c6-84e4-386aec779b2e",
          "userId": "6aa1dbd5-3c23-4f2d-9d39-6c480830ca51",
          "type": "OTHER",
          "url": "https://49dzi.bemobtrcks.com/go/37f9798e-8dae-4e0b-9cbe-5e17a0ced3a3?id=64260312",
          "location": "POST_SIDEBAR"
        }
      ]
    },
    "hashtags": [
      {
        "hashtagId": "287439f9-3210-42e2-98ea-2c7a86628845",
        "label": "lesbian",
        "labelLower": "lesbian",
        "description": "Lesbian content only.",
        "createdAt": "2023-09-05T11:03:49.522Z",
        "updatedAt": "2025-09-15T03:00:43.014Z",
        "countPosts": 2698,
        "countFollows": 50944,
        "lastCountUpdatedAt": "2025-09-15T03:00:30.710Z",
        "thumbnailPostId": 311180,
        "sexualOrientations": [
          "STRAIGHT",
          "LESBIAN",
          "TRANS",
          "OTHER"
        ],
        "isModerated": true,
        "searchTags": []
      }
    ]
  },
  {
    "postId": 745834,
    "label": "What I’m showing here is nothing compared to what I have in store. Only the daring get the real experience..",
    "score": 3796,
    "likesCount": 3956,
    "userId": "671a8257-1712-4993-81b5-f56ffe7b55bc",
    "mediaId": "bfeb6840-3de3-49cb-9112-d71822037722",
    "duration": null,
    "viewsCount": 589488,
    "bunnyVideoId": "e8ebe52f-216b-4eae-b069-bd55da9fc5f6",
    "isBunnyVideoReady": true,
    "linkDescription": {
      "profileLinkId": "b24203ae-e1ba-45f8-a20b-13deb1a961c5",
      "userId": "671a8257-1712-4993-81b5-f56ffe7b55bc",
      "type": "FANSLY",
      "url": "https://fansly.com/WetLili",
      "location": "POST_DESCRIPTION"
    },
    "linkSidebar": {
      "profileLinkId": "245eb606-dd5f-4472-99e8-315608a9ef6f",
      "userId": "671a8257-1712-4993-81b5-f56ffe7b55bc",
      "type": "OTHER",
      "url": "https://fans.ly/WetLili/t7",
      "location": "POST_SIDEBAR"
    },
    "createdAt": "2024-11-15T20:27:11.034Z",
    "updatedAt": "2025-09-28T12:00:37.726Z",
    "deletedAt": null,
    "uploadMethod": "USER_FILE",
    "sexualOrientation": "STRAIGHT",
    "algorithm": "random-boosted-post",
    "feedbackKey": "b07fa52f76b182f1636938f90a0e0227:ed62f9e811517f7b09388d13541d45d5df1da2599c74f5dcb89fc2639f0e1b1795d8b5c8e6ef2e44bd76ed340096d480fb5b08b0b8fb5de8c5fc35cf891c76be",
    "videoStreamUrl": "https://vz-5d293dac-178.b-cdn.net/bcdn_token=_bJhhxSDGtXYRy3I_BwxwDQLS2UwycMTBZZCWXtvpiY&token_countries=IN&token_path=%2Fe8ebe52f-216b-4eae-b069-bd55da9fc5f6%2F&expires=1759065706/e8ebe52f-216b-4eae-b069-bd55da9fc5f6/playlist.m3u8",
    "thumbnailStreamUrl": "https://vz-5d293dac-178.b-cdn.net/e8ebe52f-216b-4eae-b069-bd55da9fc5f6/thumbnail.jpg?token=KYrMnL25E600cVaFz06GTH_Wi0-Pk6rFPFMT0bwN6fI&height=854&token_countries=IN&width=480&expires=1759065706",
    "publishedAt": "2024-11-15T20:29:09.552Z",
    "inCollectionsCount": 420,
    "commentsCount": 0,
    "explicitnessRating": "FULLY_EXPLICIT",
    "author": {
      "userId": "671a8257-1712-4993-81b5-f56ffe7b55bc",
      "username": "LilianaWet",
      "countPosts": 80,
      "countIncomingLikes": 70944,
      "countIncomingFollows": 14600,
      "countOutgoingLikes": 0,
      "countOutgoingFollows": 0,
      "countCollections": 0,
      "countTotalViews": 4842103,
      "thumbnailId": "aed143ab-5ad4-4a98-8fea-5bab97d46057",
      "isSignedUp": true,
      "isVerified": true,
      "isPartner": true,
      "isAmbassador": false,
      "isStaff": false,
      "lastSeenAt": "2025-09-24T14:29:51.950Z",
      "description": "Love to Squirt 💦🔥  I’m all about bringing the heat and giving you exactly what you want 😏💋 If you’re into wild, unforgettable experiences, you’ve come to the right place! Want to see more? Catch me on OnlyFans for exclusive content that you won’t want to miss 💣💥  🔥 Let’s get steamy together 🔥",
      "createdAt": "2024-11-08T20:34:57.065Z",
      "updatedAt": "2025-09-25T01:33:20.616Z",
      "deletedAt": null,
      "thumbnailUrl": "https://fikfap-media-prod.b-cdn.net/users/thumbnails/aed143ab-5ad4-4a98-8fea-5bab97d46057.jpg?token=QRlSD7TWyrCPrVDQ2jURfP6J2X1FHJPO4MpMZMT8KGk&height=224&token_countries=IN&width=224&expires=1759065706",
      "roles": [],
      "profileLinks": [
        {
          "profileLinkId": "2978b106-9835-4d9e-b0e9-88e33fef3efb",
          "userId": "671a8257-1712-4993-81b5-f56ffe7b55bc",
          "type": "FANSLY",
          "url": "https://fansly.com/WetLili",
          "location": "PROFILE"
        },
        {
          "profileLinkId": "b24203ae-e1ba-45f8-a20b-13deb1a961c5",
          "userId": "671a8257-1712-4993-81b5-f56ffe7b55bc",
          "type": "FANSLY",
          "url": "https://fansly.com/WetLili",
          "location": "POST_DESCRIPTION"
        },
        {
          "profileLinkId": "245eb606-dd5f-4472-99e8-315608a9ef6f",
          "userId": "671a8257-1712-4993-81b5-f56ffe7b55bc",
          "type": "OTHER",
          "url": "https://fans.ly/WetLili/t7",
          "location": "POST_SIDEBAR"
        }
      ]
    },
    "hashtags": [
      {
        "hashtagId": "0d08f6a6-be1f-43d1-b0e0-3a43316a6342",
        "label": "squirting",
        "labelLower": "squirting",
        "description": "Women who produce the female lovejuice.",
        "createdAt": "2023-09-05T11:03:49.629Z",
        "updatedAt": "2025-09-17T03:00:32.211Z",
        "countPosts": 3505,
        "countFollows": 79472,
        "lastCountUpdatedAt": "2025-09-17T03:00:30.591Z",
        "thumbnailPostId": 272362,
        "sexualOrientations": [
          "STRAIGHT",
          "LESBIAN",
          "TRANS",
          "OTHER"
        ],
        "isModerated": true,
        "searchTags": []
      }
    ]
  },
  {
    "postId": 664563,
    "label": "ur anime gf 💕",
    "score": 119,
    "likesCount": 139,
    "userId": "e5cac372-3a33-4322-b42c-62fb8946c8d5",
    "mediaId": "5b0cecae-011a-4129-8712-6996ac28a528",
    "duration": null,
    "viewsCount": 13953,
    "bunnyVideoId": "225a9b64-571b-4a79-a281-23b9d13d606b",
    "isBunnyVideoReady": true,
    "linkDescription": {
      "profileLinkId": "c795e5f8-33fa-4546-a9d1-e3e2e4beb386",
      "userId": "e5cac372-3a33-4322-b42c-62fb8946c8d5",
      "type": "ONLYFANS",
      "url": "https://onlyfans.com/kikipearl/c2",
      "location": "POST_DESCRIPTION"
    },
    "linkSidebar": null,
    "createdAt": "2024-08-16T22:30:49.539Z",
    "updatedAt": "2025-09-28T01:08:18.872Z",
    "deletedAt": null,
    "uploadMethod": "USER_FILE",
    "sexualOrientation": "STRAIGHT",
    "algorithm": "random-minimum-score-posts-100",
    "videoStreamUrl": "https://vz-5d293dac-178.b-cdn.net/bcdn_token=8R_bC7VbEINO7NfbFDTaN_3B9XsxD2LXXscpKrrNXuE&token_countries=IN&token_path=%2F225a9b64-571b-4a79-a281-23b9d13d606b%2F&expires=1759065730/225a9b64-571b-4a79-a281-23b9d13d606b/playlist.m3u8",
    "thumbnailStreamUrl": "https://vz-5d293dac-178.b-cdn.net/225a9b64-571b-4a79-a281-23b9d13d606b/thumbnail.jpg?token=mEPR2fcSlmX7S6i-jtonUdaaFDi4RB33cD_c5uCvxH0&height=854&token_countries=IN&width=480&expires=1759065730",
    "publishedAt": "2025-07-04T15:07:25.260Z",
    "inCollectionsCount": 6,
    "commentsCount": 0,
    "explicitnessRating": null,
    "author": {
      "userId": "e5cac372-3a33-4322-b42c-62fb8946c8d5",
      "username": "Kikipearl",
      "countPosts": 71,
      "countIncomingLikes": 4460,
      "countIncomingFollows": 1741,
      "countOutgoingLikes": 2,
      "countOutgoingFollows": 0,
      "countCollections": 0,
      "countTotalViews": 738035,
      "thumbnailId": "c06a35e7-2bd6-4068-889b-886d33d75c5c",
      "isSignedUp": true,
      "isVerified": true,
      "isPartner": true,
      "isAmbassador": false,
      "isStaff": false,
      "lastSeenAt": "2025-08-23T18:12:50.801Z",
      "description": "Engineer student (T~T) and your future gf 🫰🏻",
      "createdAt": "2024-03-26T18:15:06.421Z",
      "updatedAt": "2025-09-25T01:33:20.521Z",
      "deletedAt": null,
      "thumbnailUrl": "https://fikfap-media-prod.b-cdn.net/users/thumbnails/c06a35e7-2bd6-4068-889b-886d33d75c5c.jpg?token=WgsKo5_-7KK9hd3tSBlJG1U4PUiumFvotw8VTOG5sVI&height=224&token_countries=IN&width=224&expires=1759065730",
      "roles": [],
      "profileLinks": [
        {
          "profileLinkId": "a28cc194-5fd8-4e48-9b89-50ae996b2132",
          "userId": "e5cac372-3a33-4322-b42c-62fb8946c8d5",
          "type": "ONLYFANS",
          "url": "https://onlyfans.com/kikipearl/c2",
          "location": "PROFILE"
        },
        {
          "profileLinkId": "c795e5f8-33fa-4546-a9d1-e3e2e4beb386",
          "userId": "e5cac372-3a33-4322-b42c-62fb8946c8d5",
          "type": "ONLYFANS",
          "url": "https://onlyfans.com/kikipearl/c2",
          "location": "POST_DESCRIPTION"
        }
      ]
    },
    "hashtags": [
      {
        "hashtagId": "8db85709-a221-46ba-ba7d-2e50515ce788",
        "label": "asianhottie",
        "labelLower": "asianhottie",
        "description": "This hashtag embraces the allure of Asian beauty, paying tribute to the captivating individuals from these diverse and enchanting regions.",
        "createdAt": "2023-09-05T11:03:49.786Z",
        "updatedAt": "2025-09-17T03:00:34.675Z",
        "countPosts": 4660,
        "countFollows": 32127,
        "lastCountUpdatedAt": "2025-09-17T03:00:30.591Z",
        "thumbnailPostId": 72874,
        "sexualOrientations": [
          "STRAIGHT",
          "LESBIAN",
          "GAY",
          "TRANS",
          "OTHER"
        ],
        "isModerated": true,
        "searchTags": []
      }
    ]
  },
  {
    "postId": 269084,
    "label": "Curious to see if you could handle a Jamaican girl like me ;)",
    "score": 1931,
    "likesCount": 1951,
    "userId": "6bf74b5e-831f-4315-82cd-1d087b66e79a",
    "mediaId": "c6e8b75f-74b1-4993-bfc8-7c5a692a5604",
    "duration": 20,
    "viewsCount": 370317,
    "bunnyVideoId": "0d5a7214-9195-4307-bae0-dd35dc492ca2",
    "isBunnyVideoReady": true,
    "linkDescription": null,
    "linkSidebar": null,
    "createdAt": "2023-05-31T14:44:46.350Z",
    "updatedAt": "2025-09-28T12:00:37.726Z",
    "deletedAt": null,
    "uploadMethod": "CRAWLER_REDDIT",
    "sexualOrientation": "STRAIGHT",
    "algorithm": "random-minimum-score-posts-100",
    "videoStreamUrl": "https://vz-5d293dac-178.b-cdn.net/bcdn_token=9j38HIbcfivkgM46sk20FHh-KHDkq6kuyUnLUIZG0c0&token_countries=IN&token_path=%2F0d5a7214-9195-4307-bae0-dd35dc492ca2%2F&expires=1759065730/0d5a7214-9195-4307-bae0-dd35dc492ca2/playlist.m3u8",
    "thumbnailStreamUrl": "https://vz-5d293dac-178.b-cdn.net/0d5a7214-9195-4307-bae0-dd35dc492ca2/thumbnail.jpg?token=uzFBhbORk6I_nmIbSwhWf2k_rgWbf1sWaSe-RO87HY4&height=854&token_countries=IN&width=480&expires=1759065730",
    "publishedAt": "2024-11-06T18:19:29.638Z",
    "inCollectionsCount": 181,
    "commentsCount": 0,
    "explicitnessRating": "PARTIAL_NUDITY",
    "author": {
      "userId": "6bf74b5e-831f-4315-82cd-1d087b66e79a",
      "username": "babylyraxxx",
      "countPosts": 261,
      "countIncomingLikes": 423192,
      "countIncomingFollows": 85182,
      "countOutgoingLikes": 0,
      "countOutgoingFollows": 0,
      "countCollections": 0,
      "countTotalViews": 107385721,
      "thumbnailId": "d4eb3cf2-a60b-492f-b2cc-1c210c4646c2",
      "isSignedUp": true,
      "isVerified": true,
      "isPartner": true,
      "isAmbassador": false,
      "isStaff": false,
      "lastSeenAt": "2024-11-06T17:20:18.014Z",
      "description": "Lyra Amorr",
      "createdAt": "2023-01-28T07:27:43.750Z",
      "updatedAt": "2025-09-25T01:33:21.708Z",
      "deletedAt": null,
      "thumbnailUrl": "https://fikfap-media-prod.b-cdn.net/users/thumbnails/d4eb3cf2-a60b-492f-b2cc-1c210c4646c2.jpg?token=ZJ0u-MSDtoonQE5ZHv-8eEP-eOiN7CSTjUP2hdHz4GI&height=224&token_countries=IN&width=224&expires=1759065730",
      "roles": [],
      "profileLinks": [
        {
          "profileLinkId": "3140a18e-9147-4dea-9945-fe617912b316",
          "userId": "6bf74b5e-831f-4315-82cd-1d087b66e79a",
          "type": "ONLYFANS",
          "url": "https://onlyfans.com/babylyraxxx",
          "location": "PROFILE"
        },
        {
          "profileLinkId": "c87dd9bc-8a9a-40a7-96e8-33f26a2c00b0",
          "userId": "6bf74b5e-831f-4315-82cd-1d087b66e79a",
          "type": "TWITTER",
          "url": "https://twitter.com/babylyraxxx",
          "location": "PROFILE"
        }
      ]
    },
    "hashtags": [
      {
        "hashtagId": "f96c79a8-476b-4ee1-a53e-fcbf4d8f1e3f",
        "label": "ebony",
        "labelLower": "ebony",
        "description": "This hashtag embraces the allure of black/African beauty.",
        "createdAt": "2023-09-05T11:03:52.200Z",
        "updatedAt": "2025-09-17T03:00:42.324Z",
        "countPosts": 2223,
        "countFollows": 20311,
        "lastCountUpdatedAt": "2025-09-17T03:00:30.591Z",
        "thumbnailPostId": 632448,
        "sexualOrientations": [
          "STRAIGHT",
          "LESBIAN",
          "GAY",
          "TRANS",
          "OTHER"
        ],
        "isModerated": true,
        "searchTags": []
      }
    ]
  },
  {
    "postId": 242474,
    "label": "Horny today, wbu? 😈😈😈",
    "score": 1419,
    "likesCount": 1479,
    "userId": "ba2d66ff-55f0-4bd1-925e-855555a23f3c",
    "mediaId": "74adabe3-78fc-4a2c-bf56-af52dd016b69",
    "duration": 14,
    "viewsCount": 334249,
    "bunnyVideoId": "90f758fb-29bb-49f8-a649-fc5319e56325",
    "isBunnyVideoReady": true,
    "linkDescription": {
      "profileLinkId": "a43beb8b-8966-4716-9e41-e0ed232c2cae",
      "userId": "ba2d66ff-55f0-4bd1-925e-855555a23f3c",
      "type": "ONLYFANS",
      "url": "https://onlyfans.com/sashabull78",
      "location": "POST_DESCRIPTION"
    },
    "linkSidebar": {
      "profileLinkId": "a62c6053-ed08-4dc8-a920-7d75fbb524de",
      "userId": "ba2d66ff-55f0-4bd1-925e-855555a23f3c",
      "type": "OTHER",
      "url": "https://twitter.com/sashabull78",
      "location": "POST_SIDEBAR"
    },
    "createdAt": "2023-03-03T17:44:32.819Z",
    "updatedAt": "2025-09-28T01:08:21.031Z",
    "deletedAt": null,
    "uploadMethod": "USER_FILE",
    "sexualOrientation": "STRAIGHT",
    "algorithm": "random-minimum-score-posts-100",
    "videoStreamUrl": "https://vz-5d293dac-178.b-cdn.net/bcdn_token=f_Ovc5rLbwLpUZkcZbvcDPlvbM_-51vpWUFvDgfTYgk&token_countries=IN&token_path=%2F90f758fb-29bb-49f8-a649-fc5319e56325%2F&expires=1759065730/90f758fb-29bb-49f8-a649-fc5319e56325/playlist.m3u8",
    "thumbnailStreamUrl": "https://vz-5d293dac-178.b-cdn.net/90f758fb-29bb-49f8-a649-fc5319e56325/thumbnail.jpg?token=X2Dufku1_SeOdzr51bunc7FTGTpxLPiUcA9-7uuWj_U&height=854&token_countries=IN&width=480&expires=1759065730",
    "publishedAt": "2024-09-26T14:28:41.968Z",
    "inCollectionsCount": 156,
    "commentsCount": 0,
    "explicitnessRating": "PARTIAL_NUDITY",
    "author": {
      "userId": "ba2d66ff-55f0-4bd1-925e-855555a23f3c",
      "username": "sashabull78",
      "countPosts": 90,
      "countIncomingLikes": 118339,
      "countIncomingFollows": 26187,
      "countOutgoingLikes": 0,
      "countOutgoingFollows": 0,
      "countCollections": 0,
      "countTotalViews": 21580080,
      "thumbnailId": "08dd168a-7d59-4030-85b3-aaccf3e9b70e",
      "isSignedUp": true,
      "isVerified": true,
      "isPartner": true,
      "isAmbassador": false,
      "isStaff": false,
      "lastSeenAt": "2025-09-17T17:51:35.117Z",
      "description": "🇬🇧THE MILF 🇬🇧 The best nipples on the internet 😏50% OFF NOW!!!! Subscribe to my O/F or my Fansly to access all of my media with NO PPV, FREE Audio dick rate & 23min sextape on subbing 😈 chat with me and I also make custom content 🔥🔥",
      "createdAt": "2023-02-07T16:34:55.626Z",
      "updatedAt": "2025-09-25T01:33:20.494Z",
      "deletedAt": null,
      "thumbnailUrl": "https://fikfap-media-prod.b-cdn.net/users/thumbnails/08dd168a-7d59-4030-85b3-aaccf3e9b70e.jpg?token=P9fZSz-hpOfBHMiy85nleg9qNLGc5rohebbgDd5r2tk&height=224&token_countries=IN&width=224&expires=1759065730",
      "roles": [],
      "profileLinks": [
        {
          "profileLinkId": "9fe34581-ceaa-48dd-ad0c-3f839f9ddad7",
          "userId": "ba2d66ff-55f0-4bd1-925e-855555a23f3c",
          "type": "ONLYFANS",
          "url": "https://onlyfans.com/sashabull78",
          "location": "PROFILE"
        },
        {
          "profileLinkId": "6f57d05a-a17e-4269-a0db-d37f8684e64d",
          "userId": "ba2d66ff-55f0-4bd1-925e-855555a23f3c",
          "type": "TWITTER",
          "url": "https://twitter.com/sashabull78",
          "location": "PROFILE"
        },
        {
          "profileLinkId": "a62c6053-ed08-4dc8-a920-7d75fbb524de",
          "userId": "ba2d66ff-55f0-4bd1-925e-855555a23f3c",
          "type": "OTHER",
          "url": "https://twitter.com/sashabull78",
          "location": "POST_SIDEBAR"
        },
        {
          "profileLinkId": "a43beb8b-8966-4716-9e41-e0ed232c2cae",
          "userId": "ba2d66ff-55f0-4bd1-925e-855555a23f3c",
          "type": "ONLYFANS",
          "url": "https://onlyfans.com/sashabull78",
          "location": "POST_DESCRIPTION"
        },
        {
          "profileLinkId": "5bcb8ddb-1f4b-4209-bae6-4ef5ce9313fb",
          "userId": "ba2d66ff-55f0-4bd1-925e-855555a23f3c",
          "type": "FANSLY",
          "url": "https://fansly.com/SashaBull",
          "location": "PROFILE"
        }
      ]
    },
    "hashtags": [
      {
        "hashtagId": "a9d3da2e-1122-49e9-b074-c492ef2221b7",
        "label": "godpussy",
        "labelLower": "godpussy",
        "description": "Pussy that is so holy it has reached demi-god status.",
        "createdAt": "2023-09-05T11:03:49.366Z",
        "updatedAt": "2025-09-17T03:00:43.476Z",
        "countPosts": 25036,
        "countFollows": 59407,
        "lastCountUpdatedAt": "2025-09-17T03:00:30.591Z",
        "thumbnailPostId": 313621,
        "sexualOrientations": [
          "STRAIGHT",
          "LESBIAN",
          "TRANS",
          "OTHER"
        ],
        "isModerated": true,
        "searchTags": []
      }
    ]
  },
  {
    "postId": 299320,
    "label": "Taking Hard Cock In My MILF Ass!",
    "score": 1012,
    "likesCount": 1012,
    "userId": "c4196454-1945-4a78-9e5d-6aefbd5fc1f4",
    "mediaId": "6bd9f402-5854-49fc-839e-e2447e749692",
    "duration": 56,
    "viewsCount": 185788,
    "bunnyVideoId": "22cca854-8775-4aa9-ba95-48e7c29346b7",
    "isBunnyVideoReady": true,
    "linkDescription": {
      "profileLinkId": "bfe5e22c-2bfe-4991-9fcd-6cb54a3b792a",
      "userId": "c4196454-1945-4a78-9e5d-6aefbd5fc1f4",
      "type": "ONLYFANS",
      "url": "https://www.onlyfans.com/serenesiren/",
      "location": "POST_DESCRIPTION"
    },
    "linkSidebar": {
      "profileLinkId": "09d35dd2-11ef-4eae-b6f7-d7a0f54a118f",
      "userId": "c4196454-1945-4a78-9e5d-6aefbd5fc1f4",
      "type": "OTHER",
      "url": "https://www.twitter.com/serenesirenx",
      "location": "POST_SIDEBAR"
    },
    "createdAt": "2023-08-13T03:02:26.549Z",
    "updatedAt": "2025-09-28T01:08:25.729Z",
    "deletedAt": null,
    "uploadMethod": "USER_FILE",
    "sexualOrientation": "STRAIGHT",
    "algorithm": "random-minimum-score-posts-100",
    "videoStreamUrl": "https://vz-5d293dac-178.b-cdn.net/bcdn_token=ylD5DZfrvLjA4vjloefPcUx5JPycHvJPEWKDrJIzOqc&token_countries=IN&token_path=%2F22cca854-8775-4aa9-ba95-48e7c29346b7%2F&expires=1759065730/22cca854-8775-4aa9-ba95-48e7c29346b7/playlist.m3u8",
    "thumbnailStreamUrl": "https://vz-5d293dac-178.b-cdn.net/22cca854-8775-4aa9-ba95-48e7c29346b7/thumbnail.jpg?token=2UIxCKj-DSsuygLBCo3jjUKZtum_BEYMDTM9PuBXVuw&height=854&token_countries=IN&width=480&expires=1759065730",
    "publishedAt": "2024-10-15T21:32:19.832Z",
    "inCollectionsCount": 116,
    "commentsCount": 0,
    "explicitnessRating": "FULLY_EXPLICIT",
    "author": {
      "userId": "c4196454-1945-4a78-9e5d-6aefbd5fc1f4",
      "username": "SereneSiren",
      "countPosts": 89,
      "countIncomingLikes": 111599,
      "countIncomingFollows": 24249,
      "countOutgoingLikes": 29,
      "countOutgoingFollows": 6,
      "countCollections": 0,
      "countTotalViews": 19864886,
      "thumbnailId": "931d8a1b-eccd-41f1-9a31-860df942727e",
      "isSignedUp": true,
      "isVerified": true,
      "isPartner": true,
      "isAmbassador": false,
      "isStaff": false,
      "lastSeenAt": "2025-08-23T05:55:16.811Z",
      "description": null,
      "createdAt": "2023-08-08T19:46:49.270Z",
      "updatedAt": "2025-09-25T01:33:20.720Z",
      "deletedAt": null,
      "thumbnailUrl": "https://fikfap-media-prod.b-cdn.net/users/thumbnails/931d8a1b-eccd-41f1-9a31-860df942727e.jpg?token=DqNoelaa8B_JhSgoMduULQwNC-Cd3LK9vOfGrsWlNhg&height=224&token_countries=IN&width=224&expires=1759065730",
      "roles": [],
      "profileLinks": [
        {
          "profileLinkId": "f4b615a5-3888-446e-8446-9fbe13298a6d",
          "userId": "c4196454-1945-4a78-9e5d-6aefbd5fc1f4",
          "type": "ONLYFANS",
          "url": "https://www.onlyfans.com/serenesiren/",
          "location": "PROFILE"
        },
        {
          "profileLinkId": "bfe5e22c-2bfe-4991-9fcd-6cb54a3b792a",
          "userId": "c4196454-1945-4a78-9e5d-6aefbd5fc1f4",
          "type": "ONLYFANS",
          "url": "https://www.onlyfans.com/serenesiren/",
          "location": "POST_DESCRIPTION"
        },
        {
          "profileLinkId": "09d35dd2-11ef-4eae-b6f7-d7a0f54a118f",
          "userId": "c4196454-1945-4a78-9e5d-6aefbd5fc1f4",
          "type": "OTHER",
          "url": "https://www.twitter.com/serenesirenx",
          "location": "POST_SIDEBAR"
        },
        {
          "profileLinkId": "75ebb030-1521-43cb-8f95-0777cfcd8523",
          "userId": "c4196454-1945-4a78-9e5d-6aefbd5fc1f4",
          "type": "PORNHUB",
          "url": "https://www.pornhub.com/pornstar/serene-siren",
          "location": "PROFILE"
        },
        {
          "profileLinkId": "b4477908-9a7e-4fe6-be1d-be2cf7316a03",
          "userId": "c4196454-1945-4a78-9e5d-6aefbd5fc1f4",
          "type": "OTHER",
          "url": "https://www.loyalfans.com/serenesiren",
          "location": "PROFILE"
        }
      ]
    },
    "hashtags": [
      {
        "hashtagId": "dd855653-13b7-496f-965b-268aeedd86aa",
        "label": "anal",
        "labelLower": "anal",
        "description": "Everything from anal sex to the use of toys for anal stimulation.",
        "createdAt": "2023-09-05T11:03:49.313Z",
        "updatedAt": "2025-09-17T03:00:40.458Z",
        "countPosts": 16255,
        "countFollows": 72727,
        "lastCountUpdatedAt": "2025-09-17T03:00:30.591Z",
        "thumbnailPostId": 324426,
        "sexualOrientations": [
          "STRAIGHT",
          "LESBIAN",
          "GAY",
          "TRANS",
          "OTHER"
        ],
        "isModerated": true,
        "searchTags": []
      }
    ]
  },
  {
    "postId": 812705,
    "label": "Can’t get enough? My OF has everything you want. Bio link 🥵",
    "score": 223,
    "likesCount": 243,
    "userId": "aeab45c5-28be-47ac-9d80-879982f55bca",
    "mediaId": "bbfbc21a-349e-4968-9562-854ddb9ccd9a",
    "duration": null,
    "viewsCount": 28451,
    "bunnyVideoId": "071929f1-a862-4681-b3bd-40327e4816e8",
    "isBunnyVideoReady": true,
    "linkDescription": {
      "profileLinkId": "8229fdea-9e65-4569-9daf-c5d551a9281c",
      "userId": "aeab45c5-28be-47ac-9d80-879982f55bca",
      "type": "ONLYFANS",
      "url": "https://onlyfans.com/angelsdaria/c123",
      "location": "POST_DESCRIPTION"
    },
    "linkSidebar": {
      "profileLinkId": "0a2bb6bf-7723-4154-b830-58df95dde981",
      "userId": "aeab45c5-28be-47ac-9d80-879982f55bca",
      "type": "OTHER",
      "url": "https://onlyfans.com/angelsdaria/c123",
      "location": "POST_SIDEBAR"
    },
    "createdAt": "2025-01-07T07:10:09.282Z",
    "updatedAt": "2025-09-28T01:08:19.692Z",
    "deletedAt": null,
    "uploadMethod": "USER_FILE",
    "sexualOrientation": "STRAIGHT",
    "algorithm": "random-minimum-score-posts-100",
    "videoStreamUrl": "https://vz-5d293dac-178.b-cdn.net/bcdn_token=6YbyJRQZIhuZ4QedoaKM1nMGq8mKu4DssAuNb8BcnbI&token_countries=IN&token_path=%2F071929f1-a862-4681-b3bd-40327e4816e8%2F&expires=1759065730/071929f1-a862-4681-b3bd-40327e4816e8/playlist.m3u8",
    "thumbnailStreamUrl": "https://vz-5d293dac-178.b-cdn.net/071929f1-a862-4681-b3bd-40327e4816e8/thumbnail.jpg?token=QU5044Niv_t_W0NKlGW2wziRC5UD5RnoT3_nCV8nCUU&height=854&token_countries=IN&width=480&expires=1759065730",
    "publishedAt": "2025-01-07T07:14:28.821Z",
    "inCollectionsCount": 22,
    "commentsCount": 0,
    "explicitnessRating": null,
    "author": {
      "userId": "aeab45c5-28be-47ac-9d80-879982f55bca",
      "username": "ANGEL",
      "countPosts": 1506,
      "countIncomingLikes": 402035,
      "countIncomingFollows": 58048,
      "countOutgoingLikes": 2740,
      "countOutgoingFollows": 406,
      "countCollections": 0,
      "countTotalViews": 38978140,
      "thumbnailId": "24b87113-7969-4997-b6de-c5cfb81a6cce",
      "isSignedUp": true,
      "isVerified": true,
      "isPartner": true,
      "isAmbassador": false,
      "isStaff": false,
      "lastSeenAt": "2025-09-21T09:12:50.343Z",
      "description": "🔞💦My onlyfans page !👆🏻lots of exclusive content and chat with me🔥🔞",
      "createdAt": "2023-07-14T11:27:00.034Z",
      "updatedAt": "2025-09-26T01:32:15.470Z",
      "deletedAt": null,
      "thumbnailUrl": "https://fikfap-media-prod.b-cdn.net/users/thumbnails/24b87113-7969-4997-b6de-c5cfb81a6cce.jpg?token=mme6K6sJxGCG1-kqjCl7-3g_mOD8kfCBOqdCEmF7U5I&height=224&token_countries=IN&width=224&expires=1759065730",
      "roles": [],
      "profileLinks": [
        {
          "profileLinkId": "e56b3392-ca43-42ea-8bc6-3a1ff2e2864b",
          "userId": "aeab45c5-28be-47ac-9d80-879982f55bca",
          "type": "FANSLY",
          "url": "https://fansly.com/subscriptions/giftcode/NTQ4ODc3NzM1Nzk2MTU4NDY0OjE6MTozYThkYjQzMTRh",
          "location": "PROFILE"
        },
        {
          "profileLinkId": "ca6e225f-bb43-4141-8f47-f947f4771d28",
          "userId": "aeab45c5-28be-47ac-9d80-879982f55bca",
          "type": "ONLYFANS",
          "url": "https://onlyfans.com/angelsdaria/c123",
          "location": "PROFILE"
        },
        {
          "profileLinkId": "8229fdea-9e65-4569-9daf-c5d551a9281c",
          "userId": "aeab45c5-28be-47ac-9d80-879982f55bca",
          "type": "ONLYFANS",
          "url": "https://onlyfans.com/angelsdaria/c123",
          "location": "POST_DESCRIPTION"
        },
        {
          "profileLinkId": "93bc7f7f-d211-4c37-852e-102a15293da4",
          "userId": "aeab45c5-28be-47ac-9d80-879982f55bca",
          "type": "OTHER",
          "url": "https://onlyfans.com/angelsdaria/c123",
          "location": "PROFILE"
        },
        {
          "profileLinkId": "0a2bb6bf-7723-4154-b830-58df95dde981",
          "userId": "aeab45c5-28be-47ac-9d80-879982f55bca",
          "type": "OTHER",
          "url": "https://onlyfans.com/angelsdaria/c123",
          "location": "POST_SIDEBAR"
        }
      ]
    },
    "hashtags": [
      {
        "hashtagId": "a2cc5702-cea0-48a1-b904-93c52e3a6b37",
        "label": "doggystyle",
        "labelLower": "doggystyle",
        "description": "For the lovers of the most popular sex position.",
        "createdAt": "2023-09-05T11:03:52.307Z",
        "updatedAt": "2025-09-17T03:00:42.037Z",
        "countPosts": 6393,
        "countFollows": 30439,
        "lastCountUpdatedAt": "2025-09-17T03:00:30.591Z",
        "thumbnailPostId": 313622,
        "sexualOrientations": [
          "STRAIGHT",
          "LESBIAN",
          "GAY",
          "TRANS",
          "OTHER"
        ],
        "isModerated": true,
        "searchTags": []
      }
    ]
  },
  {
    "postId": 338273,
    "label": "oh my wet pussy",
    "score": 436,
    "likesCount": 436,
    "userId": "3b55b9fe-ffdb-4923-b44f-c9e509dbdf94",
    "mediaId": "daaf68d9-e197-4642-a212-fd31a918a396",
    "duration": 20,
    "viewsCount": 80753,
    "bunnyVideoId": "4a7e9c94-f3d7-4196-85db-a3b026051b6f",
    "isBunnyVideoReady": true,
    "linkDescription": {
      "profileLinkId": "e77f606a-a59d-42e7-be9c-1753ba8d3bb1",
      "userId": "3b55b9fe-ffdb-4923-b44f-c9e509dbdf94",
      "type": "ONLYFANS",
      "url": "https://onlyfans.com/virgin_desire/c7",
      "location": "POST_DESCRIPTION"
    },
    "linkSidebar": {
      "profileLinkId": "7d25c15a-680b-493e-b9fc-a96ae4ee6384",
      "userId": "3b55b9fe-ffdb-4923-b44f-c9e509dbdf94",
      "type": "OTHER",
      "url": "https://onlyfans.com/virgin_desire/c7",
      "location": "POST_SIDEBAR"
    },
    "createdAt": "2023-10-18T09:32:06.140Z",
    "updatedAt": "2025-09-28T01:08:19.131Z",
    "deletedAt": null,
    "uploadMethod": "USER_FILE",
    "sexualOrientation": "STRAIGHT",
    "algorithm": "random-minimum-score-posts-100",
    "videoStreamUrl": "https://vz-5d293dac-178.b-cdn.net/bcdn_token=YFDTtu0AXMRsWOu9XWY8fvcNiyaUdsOvA3hT5qyiMNY&token_countries=IN&token_path=%2F4a7e9c94-f3d7-4196-85db-a3b026051b6f%2F&expires=1759065730/4a7e9c94-f3d7-4196-85db-a3b026051b6f/playlist.m3u8",
    "thumbnailStreamUrl": "https://vz-5d293dac-178.b-cdn.net/4a7e9c94-f3d7-4196-85db-a3b026051b6f/thumbnail.jpg?token=xEW41tGPNd8ndoJ4LrGS3Ei0PBp49PrwygDwxh2olso&height=854&token_countries=IN&width=480&expires=1759065730",
    "publishedAt": "2024-09-22T20:54:08.388Z",
    "inCollectionsCount": 66,
    "commentsCount": 0,
    "explicitnessRating": "PARTIAL_NUDITY",
    "author": {
      "userId": "3b55b9fe-ffdb-4923-b44f-c9e509dbdf94",
      "username": "Nika_Desire",
      "countPosts": 196,
      "countIncomingLikes": 20874,
      "countIncomingFollows": 7374,
      "countOutgoingLikes": 0,
      "countOutgoingFollows": 0,
      "countCollections": 0,
      "countTotalViews": 3910822,
      "thumbnailId": "0be3a2c2-b1ad-4186-ae8c-aef38fe52002",
      "isSignedUp": true,
      "isVerified": true,
      "isPartner": true,
      "isAmbassador": false,
      "isStaff": false,
      "lastSeenAt": "2023-11-06T14:29:42.480Z",
      "description": "Hi🌸 my name is Nika✨ you have to be honest with me and I will show you paradise here👼👄 so let's get to know each other and be close🙈? Write to me on my onlyfans account.",
      "createdAt": "2023-09-28T09:35:08.565Z",
      "updatedAt": "2025-09-25T01:33:20.268Z",
      "deletedAt": null,
      "thumbnailUrl": "https://fikfap-media-prod.b-cdn.net/users/thumbnails/0be3a2c2-b1ad-4186-ae8c-aef38fe52002.jpg?token=u2s33TPsy8Rg7rpJtFV7DhpnVX2eO9vxNlv5SM0Xg8g&height=224&token_countries=IN&width=224&expires=1759065730",
      "roles": [],
      "profileLinks": [
        {
          "profileLinkId": "f08f4ed2-86b6-4202-996d-894992d79843",
          "userId": "3b55b9fe-ffdb-4923-b44f-c9e509dbdf94",
          "type": "ONLYFANS",
          "url": "https://onlyfans.com/virgin_desire/c7",
          "location": "PROFILE"
        },
        {
          "profileLinkId": "e77f606a-a59d-42e7-be9c-1753ba8d3bb1",
          "userId": "3b55b9fe-ffdb-4923-b44f-c9e509dbdf94",
          "type": "ONLYFANS",
          "url": "https://onlyfans.com/virgin_desire/c7",
          "location": "POST_DESCRIPTION"
        },
        {
          "profileLinkId": "c412719a-e70e-4229-94d4-3c1ae4b57c72",
          "userId": "3b55b9fe-ffdb-4923-b44f-c9e509dbdf94",
          "type": "INSTAGRAM",
          "url": "https://www.instagram.com/nika_angel2005/",
          "location": "PROFILE"
        },
        {
          "profileLinkId": "7d25c15a-680b-493e-b9fc-a96ae4ee6384",
          "userId": "3b55b9fe-ffdb-4923-b44f-c9e509dbdf94",
          "type": "OTHER",
          "url": "https://onlyfans.com/virgin_desire/c7",
          "location": "POST_SIDEBAR"
        }
      ]
    },
    "hashtags": [
      {
        "hashtagId": "dda87ea0-18b6-4cd9-96c1-d430c7640e53",
        "label": "pussyjob",
        "labelLower": "pussyjob",
        "description": null,
        "createdAt": "2023-09-05T11:03:54.726Z",
        "updatedAt": "2025-09-17T03:00:31.169Z",
        "countPosts": 8710,
        "countFollows": 16590,
        "lastCountUpdatedAt": "2025-09-17T03:00:30.591Z",
        "thumbnailPostId": 656864,
        "sexualOrientations": [
          "STRAIGHT",
          "LESBIAN",
          "TRANS",
          "OTHER"
        ],
        "isModerated": false,
        "searchTags": []
      }
    ]
  },
  {
    "postId": 867824,
    "label": "Keeping it subtle here, but if you want the real view, let’s just say things get very exciting where I don’t hold back 😈",
    "score": 875,
    "likesCount": 895,
    "userId": "fea9f91a-f6d8-4a25-b35d-db9026dc120c",
    "mediaId": "a9c22d24-c5c0-4517-9787-5d45d564e285",
    "duration": null,
    "viewsCount": 81962,
    "bunnyVideoId": "ee668dbe-eaa7-40d8-9135-e28d819e198d",
    "isBunnyVideoReady": true,
    "linkDescription": {
      "profileLinkId": "ac7d7d56-1d43-400f-be5c-c7ccfe715c3e",
      "userId": "fea9f91a-f6d8-4a25-b35d-db9026dc120c",
      "type": "ONLYFANS",
      "url": "https://onlyfans.com/katrina_soul/trial/wgipuoxerx3e9ct6cxozej1vsyo4uwew",
      "location": "POST_DESCRIPTION"
    },
    "linkSidebar": {
      "profileLinkId": "8af5c25d-78db-4450-88b9-c536fdf5f49e",
      "userId": "fea9f91a-f6d8-4a25-b35d-db9026dc120c",
      "type": "OTHER",
      "url": "https://virginlinks.github.io/mylinks/diana6/",
      "location": "POST_SIDEBAR"
    },
    "createdAt": "2025-02-01T18:29:11.236Z",
    "updatedAt": "2025-09-28T01:08:26.482Z",
    "deletedAt": null,
    "uploadMethod": "USER_FILE",
    "sexualOrientation": "STRAIGHT",
    "algorithm": "random-minimum-score-posts-100",
    "videoStreamUrl": "https://vz-5d293dac-178.b-cdn.net/bcdn_token=Vm0PUNLe7JStbjplnMRaQHgtdyI5w6C6-ehWDQKjFlg&token_countries=IN&token_path=%2Fee668dbe-eaa7-40d8-9135-e28d819e198d%2F&expires=1759065730/ee668dbe-eaa7-40d8-9135-e28d819e198d/playlist.m3u8",
    "thumbnailStreamUrl": "https://vz-5d293dac-178.b-cdn.net/ee668dbe-eaa7-40d8-9135-e28d819e198d/thumbnail.jpg?token=dzGw9QP1-9PsQPTt34wvTPgoqtnWXAEl7Zwq4bnBbnI&height=854&token_countries=IN&width=480&expires=1759065730",
    "publishedAt": "2025-02-01T18:55:42.203Z",
    "inCollectionsCount": 134,
    "commentsCount": 0,
    "explicitnessRating": "FULLY_EXPLICIT",
    "author": {
      "userId": "fea9f91a-f6d8-4a25-b35d-db9026dc120c",
      "username": "DiXXX",
      "countPosts": 182,
      "countIncomingLikes": 259457,
      "countIncomingFollows": 46794,
      "countOutgoingLikes": 3,
      "countOutgoingFollows": 2,
      "countCollections": 0,
      "countTotalViews": 31894362,
      "thumbnailId": "a5ce5250-517d-4f95-99f0-00e0350350b6",
      "isSignedUp": true,
      "isVerified": true,
      "isPartner": true,
      "isAmbassador": false,
      "isStaff": false,
      "lastSeenAt": "2025-09-24T14:38:04.662Z",
      "description": "Hi, my name is Di. I love to do striptease and share my dancing on this blog 💗 By the way, this is my VIP page and here you can see not only striptease👇",
      "createdAt": "2024-02-15T19:39:09.784Z",
      "updatedAt": "2025-09-25T01:33:21.247Z",
      "deletedAt": null,
      "thumbnailUrl": "https://fikfap-media-prod.b-cdn.net/users/thumbnails/a5ce5250-517d-4f95-99f0-00e0350350b6.jpg?token=cdt6V3bw98PsaKQOni20odyiz-76uEzEATyrnL9RzFs&height=224&token_countries=IN&width=224&expires=1759065730",
      "roles": [],
      "profileLinks": [
        {
          "profileLinkId": "3bc3db43-e416-496a-a431-32f657f9ca9b",
          "userId": "fea9f91a-f6d8-4a25-b35d-db9026dc120c",
          "type": "ONLYFANS",
          "url": "https://onlyfans.com/katrina_soul/trial/wgipuoxerx3e9ct6cxozej1vsyo4uwew",
          "location": "PROFILE"
        },
        {
          "profileLinkId": "ac7d7d56-1d43-400f-be5c-c7ccfe715c3e",
          "userId": "fea9f91a-f6d8-4a25-b35d-db9026dc120c",
          "type": "ONLYFANS",
          "url": "https://onlyfans.com/katrina_soul/trial/wgipuoxerx3e9ct6cxozej1vsyo4uwew",
          "location": "POST_DESCRIPTION"
        },
        {
          "profileLinkId": "2738dc2e-0590-4fc1-b896-ef745e4a38f8",
          "userId": "fea9f91a-f6d8-4a25-b35d-db9026dc120c",
          "type": "OTHER",
          "url": "https://virginlinks.github.io/mylinks/diana6/",
          "location": "PROFILE"
        },
        {
          "profileLinkId": "8af5c25d-78db-4450-88b9-c536fdf5f49e",
          "userId": "fea9f91a-f6d8-4a25-b35d-db9026dc120c",
          "type": "OTHER",
          "url": "https://virginlinks.github.io/mylinks/diana6/",
          "location": "POST_SIDEBAR"
        }
      ]
    },
    "hashtags": [
      {
        "hashtagId": "dd855653-13b7-496f-965b-268aeedd86aa",
        "label": "anal",
        "labelLower": "anal",
        "description": "Everything from anal sex to the use of toys for anal stimulation.",
        "createdAt": "2023-09-05T11:03:49.313Z",
        "updatedAt": "2025-09-17T03:00:40.458Z",
        "countPosts": 16255,
        "countFollows": 72727,
        "lastCountUpdatedAt": "2025-09-17T03:00:30.591Z",
        "thumbnailPostId": 324426,
        "sexualOrientations": [
          "STRAIGHT",
          "LESBIAN",
          "GAY",
          "TRANS",
          "OTHER"
        ],
        "isModerated": true,
        "searchTags": []
      }
    ]
  },
  {
    "postId": 281339,
    "label": "How does your dick compare to Danny D's? SPH",
    "score": 7537,
    "likesCount": 8817,
    "userId": "94c34554-ea02-4938-8de9-2ec401a08062",
    "mediaId": "1dadfa66-6310-4fa6-9eab-e67b3fdec073",
    "duration": 22,
    "viewsCount": 2609886,
    "bunnyVideoId": "a1dfa729-c67c-4d17-98c3-ca7b76bb371a",
    "isBunnyVideoReady": true,
    "linkDescription": {
      "profileLinkId": "d31d96c8-a33d-44bc-94b2-55ceb5781d31",
      "userId": "94c34554-ea02-4938-8de9-2ec401a08062",
      "type": "ONLYFANS",
      "url": "https://onlyfans.com/ruby_onyx",
      "location": "POST_DESCRIPTION"
    },
    "linkSidebar": {
      "profileLinkId": "bf21f66e-11a4-464a-9960-374b0c6688e1",
      "userId": "94c34554-ea02-4938-8de9-2ec401a08062",
      "type": "OTHER",
      "url": "https://twitter.com/ladyrubyonyx",
      "location": "POST_SIDEBAR"
    },
    "createdAt": "2023-07-05T21:32:14.739Z",
    "updatedAt": "2025-09-28T11:00:37.240Z",
    "deletedAt": null,
    "uploadMethod": "USER_FILE",
    "sexualOrientation": "STRAIGHT",
    "algorithm": "random-silver-posts",
    "videoStreamUrl": "https://vz-5d293dac-178.b-cdn.net/bcdn_token=zqKPde9uhS2SCxvAn3vFacKSzOL0gAVHY7sHDuOSTFs&token_countries=IN&token_path=%2Fa1dfa729-c67c-4d17-98c3-ca7b76bb371a%2F&expires=1759065730/a1dfa729-c67c-4d17-98c3-ca7b76bb371a/playlist.m3u8",
    "thumbnailStreamUrl": "https://vz-5d293dac-178.b-cdn.net/a1dfa729-c67c-4d17-98c3-ca7b76bb371a/thumbnail.jpg?token=zJe35jRTIFuP5xhVJjTrurLUDPEWI045QcrSOSyQGig&height=854&token_countries=IN&width=480&expires=1759065730",
    "publishedAt": "2024-09-22T20:54:08.388Z",
    "inCollectionsCount": 1001,
    "commentsCount": 0,
    "explicitnessRating": "FULLY_EXPLICIT",
    "author": {
      "userId": "94c34554-ea02-4938-8de9-2ec401a08062",
      "username": "Ruby_Onyx",
      "countPosts": 36,
      "countIncomingLikes": 55291,
      "countIncomingFollows": 17396,
      "countOutgoingLikes": 0,
      "countOutgoingFollows": 4,
      "countCollections": 0,
      "countTotalViews": 13022639,
      "thumbnailId": "741ddd27-9e4f-40ee-b17c-ab2d15c64c57",
      "isSignedUp": true,
      "isVerified": true,
      "isPartner": true,
      "isAmbassador": false,
      "isStaff": false,
      "lastSeenAt": "2025-08-18T13:42:34.090Z",
      "description": "I'm Ruby! And I love Huge Cock! 🍆 follow my HotWife lifestyle!🔥Cuckolding is my fave!❤️‍🔥 I also enjoy FemDom, particularly Pegging and Forced Bi!😈 DM me on OF or FANSLY to say you came from FikFap for a FREE video dick rating! ",
      "createdAt": "2023-05-19T09:08:35.924Z",
      "updatedAt": "2025-09-25T01:33:20.579Z",
      "deletedAt": null,
      "thumbnailUrl": "https://fikfap-media-prod.b-cdn.net/users/thumbnails/741ddd27-9e4f-40ee-b17c-ab2d15c64c57.jpg?token=H5j7HN5vYv-xNr0va823IVJg9wc7LiZHnbI2ZyLAeAE&height=224&token_countries=IN&width=224&expires=1759065730",
      "roles": [],
      "profileLinks": [
        {
          "profileLinkId": "d31d96c8-a33d-44bc-94b2-55ceb5781d31",
          "userId": "94c34554-ea02-4938-8de9-2ec401a08062",
          "type": "ONLYFANS",
          "url": "https://onlyfans.com/ruby_onyx",
          "location": "POST_DESCRIPTION"
        },
        {
          "profileLinkId": "cd970cbb-8886-4617-95d4-b2e934a46e1d",
          "userId": "94c34554-ea02-4938-8de9-2ec401a08062",
          "type": "OTHER",
          "url": "https://getsl.ink/ruby_onyx",
          "location": "PROFILE"
        },
        {
          "profileLinkId": "0493054c-693e-4be1-8bfe-e2c79bd1ffcc",
          "userId": "94c34554-ea02-4938-8de9-2ec401a08062",
          "type": "FANSLY",
          "url": "https://fansly.com/ruby_onyx",
          "location": "PROFILE"
        },
        {
          "profileLinkId": "ac2a2fcf-d370-404d-a186-8635fa547d19",
          "userId": "94c34554-ea02-4938-8de9-2ec401a08062",
          "type": "ONLYFANS",
          "url": "https://onlyfans.com/ruby_onyx",
          "location": "PROFILE"
        },
        {
          "profileLinkId": "bf21f66e-11a4-464a-9960-374b0c6688e1",
          "userId": "94c34554-ea02-4938-8de9-2ec401a08062",
          "type": "OTHER",
          "url": "https://twitter.com/ladyrubyonyx",
          "location": "POST_SIDEBAR"
        }
      ]
    },
    "hashtags": [
      {
        "hashtagId": "eb4b1c00-947a-425e-9a3e-77c470169b67",
        "label": "massivecock",
        "labelLower": "massivecock",
        "description": "",
        "createdAt": "2023-09-05T11:03:58.860Z",
        "updatedAt": "2025-09-17T03:00:33.254Z",
        "countPosts": 1706,
        "countFollows": 7632,
        "lastCountUpdatedAt": "2025-09-17T03:00:30.591Z",
        "thumbnailPostId": 1057745,
        "sexualOrientations": [
          "STRAIGHT",
          "GAY",
          "TRANS",
          "OTHER"
        ],
        "isModerated": false,
        "searchTags": []
      }
    ]
  },
  {
    "postId": 641835,
    "label": "I'm a bit wierd but extra honry",
    "score": 176,
    "likesCount": 176,
    "userId": "c6486287-1199-4488-b211-dfa22d22c371",
    "mediaId": "54f6bbc0-e524-4ec6-83cd-faac36ea8491",
    "duration": null,
    "viewsCount": 35892,
    "bunnyVideoId": "e6ffe713-613c-4978-8b75-b876a368c02b",
    "isBunnyVideoReady": true,
    "linkDescription": {
      "profileLinkId": "045460ce-5f11-4574-8ad5-1b2c96f6d67c",
      "userId": "c6486287-1199-4488-b211-dfa22d22c371",
      "type": "ONLYFANS",
      "url": "https://onlyfans.com/action/trial/wsd9gmldeisgwiz36kgprtwd3lld6amx",
      "location": "POST_DESCRIPTION"
    },
    "linkSidebar": null,
    "createdAt": "2024-07-19T21:08:13.641Z",
    "updatedAt": "2025-09-28T01:08:18.800Z",
    "deletedAt": null,
    "uploadMethod": "USER_FILE",
    "sexualOrientation": "STRAIGHT",
    "algorithm": "random-minimum-score-posts-100",
    "videoStreamUrl": "https://vz-5d293dac-178.b-cdn.net/bcdn_token=btyZJs-nneO3BQM-DConJboMBkiRA-1SeiSKCwgjFt8&token_countries=IN&token_path=%2Fe6ffe713-613c-4978-8b75-b876a368c02b%2F&expires=1759065730/e6ffe713-613c-4978-8b75-b876a368c02b/playlist.m3u8",
    "thumbnailStreamUrl": "https://vz-5d293dac-178.b-cdn.net/e6ffe713-613c-4978-8b75-b876a368c02b/thumbnail.jpg?token=aEdDLnovp_RrCYL-zCBLE8o3c1wJOUhkCx-eDdZWdOM&height=854&token_countries=IN&width=480&expires=1759065730",
    "publishedAt": "2024-09-22T20:54:08.388Z",
    "inCollectionsCount": 18,
    "commentsCount": 0,
    "explicitnessRating": null,
    "author": {
      "userId": "c6486287-1199-4488-b211-dfa22d22c371",
      "username": "Lumi",
      "countPosts": 1685,
      "countIncomingLikes": 266157,
      "countIncomingFollows": 42256,
      "countOutgoingLikes": 0,
      "countOutgoingFollows": 0,
      "countCollections": 0,
      "countTotalViews": 26580832,
      "thumbnailId": "b8cdfbde-a3a2-4759-bf47-571f9a27afa7",
      "isSignedUp": true,
      "isVerified": true,
      "isPartner": true,
      "isAmbassador": false,
      "isStaff": false,
      "lastSeenAt": "2025-09-25T19:02:46.279Z",
      "description": "Young and beautiful 18-year-old brunette😘",
      "createdAt": "2024-07-04T18:05:06.910Z",
      "updatedAt": "2025-09-26T01:32:15.338Z",
      "deletedAt": null,
      "thumbnailUrl": "https://fikfap-media-prod.b-cdn.net/users/thumbnails/b8cdfbde-a3a2-4759-bf47-571f9a27afa7.jpg?token=AMjVXdVymYtRmmplnyYBIcvD1c1fsNBLxuYf073DJLY&height=224&token_countries=IN&width=224&expires=1759065730",
      "roles": [],
      "profileLinks": [
        {
          "profileLinkId": "44ab305a-8acc-443e-bc8c-350fed9ebfda",
          "userId": "c6486287-1199-4488-b211-dfa22d22c371",
          "type": "ONLYFANS",
          "url": "https://onlyfans.com/action/trial/wsd9gmldeisgwiz36kgprtwd3lld6amx",
          "location": "PROFILE"
        },
        {
          "profileLinkId": "045460ce-5f11-4574-8ad5-1b2c96f6d67c",
          "userId": "c6486287-1199-4488-b211-dfa22d22c371",
          "type": "ONLYFANS",
          "url": "https://onlyfans.com/action/trial/wsd9gmldeisgwiz36kgprtwd3lld6amx",
          "location": "POST_DESCRIPTION"
        },
        {
          "profileLinkId": "88486915-81ab-4109-8493-c39afb9284cb",
          "userId": "c6486287-1199-4488-b211-dfa22d22c371",
          "type": "INSTAGRAM",
          "url": "https://www.instagram.com/lumicut.e",
          "location": "PROFILE"
        }
      ]
    },
    "hashtags": [
      {
        "hashtagId": "4f1edb5b-ce64-4713-8b6d-ed818daa7b69",
        "label": "lipsthatgrip",
        "labelLower": "lipsthatgrip",
        "description": "A place for shorts of pussy-gripping goodness. ",
        "createdAt": "2023-09-05T11:03:50.752Z",
        "updatedAt": "2025-09-17T03:00:43.943Z",
        "countPosts": 1406,
        "countFollows": 29414,
        "lastCountUpdatedAt": "2025-09-17T03:00:30.591Z",
        "thumbnailPostId": 275852,
        "sexualOrientations": [
          "STRAIGHT",
          "LESBIAN",
          "TRANS",
          "OTHER"
        ],
        "isModerated": true,
        "searchTags": []
      }
    ]
  }
]