{
  "video_id": "4031489",
  "url": "https://rule34video.com/video/4031489/wedding-crashers-legendado-pt-br/",
  "title": "Wedding Crashers [LEGENDADO PT-BR]",
  "duration": "14:54",
  "views": 20816,
  "tags": [
    "anal",
    "anal creampie",
    "bdsm",
    "bdsm hardcore",
    "choking",
    "sound",
    "double anal penetration",
    "double penetration",
    "female domination",
    "futanari",
    "futanari on male",
    "futadom",
    "deepthroat",
    "rape",
    "handjob",
    "blowjob",
    "creampie",
    "threesome",
    "blackmail",
    "big breasts",
    "big penis",
    "bbw",
    "femboy",
    "netorare",
    "hairy pussy",
    "portuguese subtitles"
  ],
  "categories": [
    "Koikatsu",
    "3D",
    "iwara"
  ],
  "description": "Thanks to a fan on Twitter @TheBlackSub my works can now be done in Portuguese due to him translating it Hope you enjoy!\n\nWant to help support my animations and keep up with everything? Maybe even want your own commission? Patreon: Patreon.com/RatedF4Futa Subscribestar: https://subscribestar.adult/ratedf4futa Twitter: https://twitter.com/RatedF4Futa",
  "thumbnail_src": "https://rule34video.com/contents/videos_screenshots/4031000/4031489/preview.jpg",
  "video_src": "https://rule34video.com/get_file/47/1d089bbc3d7047b5f35746e4eaf2bbad024af893b2/4031000/4031489/4031489_1080p.mp4/?download_filename=wedding-crashers-legendado-pt-br_1080p.mp4&br=4525",
  "uploaded_by": "RatedF4Futa",
  "artists": [
    "RatedF4Futa"
  ],
  "upload_date": "2025-09-16"
}